loose.py
setup.py
loose.egg-info/PKG-INFO
loose.egg-info/SOURCES.txt
loose.egg-info/dependency_links.txt
loose.egg-info/top_level.txt