Metadata-Version: 1.1
Name: loose
Version: 0.0.2a1
Summary: Javascript style objects for python
Home-page: https://github.com/shivekkhurana/loose
Author: Shivek Khurana
Author-email: khuranashivek@gmail.com
License: MIT
Keywords: loose,js objects
Platform: UNKNOWN
Classifier: Development Status :: 3 - Alpha
Classifier: Intended Audience :: Developers
Classifier: License :: OSI Approved :: MIT License
Classifier: Programming Language :: Python :: 2.7
Classifier: Programming Language :: Python :: 3
Classifier: Programming Language :: Python :: 3.2
Classifier: Programming Language :: Python :: 3.3
Classifier: Programming Language :: Python :: 3.4
Classifier: Topic :: Utilities
